[
  {
    "id": 1,
    "name": "Lapiseira",
    "color": "Preto",
    "price": 4.5,
    "count": 50,
    "code": "LLL6543",
    "published": true,
    "date": "08/06/2023"
  },
  {
    "id": 2,
    "name": "Celular Samsung",
    "color": "Azul",
    "price": 6450,
    "count": 40,
    "code": "CCC6542",
    "published": true,
    "date": "08/06/2023"
  },
  {
    "id": 3,
    "name": "Calca",
    "color": "Cinza",
    "price": 78,
    "count": 230,
    "code": "BBB4024",
    "published": true,
    "date": "10/06/2023"
  },
  {
    "id": 4,
    "name": "Chinelo Havaianas",
    "color": "Rosa",
    "price": 30.98,
    "count": 340,
    "code": "BBB4024",
    "published": true,
    "date": "15/06/2023"
  },
  {
    "id": 5,
    "name": "Carro",
    "color": "Prata",
    "price": 56000,
    "count": 5,
    "code": "CCC7654",
    "published": true,
    "date": "16/06/2023"
  },
  {
    "id": 6,
    "name": "Livro Harry Potter",
    "color": "colorido",
    "price": 85.9,
    "count": 15,
    "code": "LLL7689",
    "published": true,
    "date": "18/06/2023"
  },
  {
    "id": 7,
    "name": "Playstation",
    "color": "Branco",
    "price": 5000,
    "count": 3,
    "code": "PPP7654",
    "published": true,
    "date": "20/06/2023"
  }
]